rvt_monitor/__init__.py
rvt_monitor/__main__.py
rvt_monitor/main.py
rvt_monitor/ble/__init__.py
rvt_monitor/ble/manager.py
rvt_monitor/ble/profiles.py
rvt_monitor/ble/protocol.py
rvt_monitor/ble/scanner.py
rvt_monitor/core/__init__.py
rvt_monitor/core/logger.py
rvt_monitor/isv2_config/__init__.py
rvt_monitor/isv2_config/cli.py
rvt_monitor/isv2_config/protocol.py
rvt_monitor/isv2_config/serial_port.py
rvt_monitor/isv2_config/server.py
rvt_monitor/isv2_config/static/index.html
rvt_monitor/server/__init__.py
rvt_monitor/server/app.py
rvt_monitor/server/state.py
rvt_monitor/server/websocket.py
rvt_monitor/server/routes/__init__.py
rvt_monitor/server/routes/config.py
rvt_monitor/server/routes/control.py
rvt_monitor/server/routes/device.py
rvt_monitor/server/routes/logs.py
rvt_monitor/static/index.html
rvt_monitor/static/css/style.css
rvt_monitor/static/js/app.js
rvt_monitor-0.2.3.dist-info/METADATA
rvt_monitor-0.2.3.dist-info/WHEEL
rvt_monitor-0.2.3.dist-info/entry_points.txt
rvt_monitor-0.2.3.dist-info/RECORD
